{
  "hideout": {
    "2": {
      "currentLevel": 2,
      "raidsSinceStarted": 0,
      "timeAvailable": 1717992154821
    },
    "4": {
      "currentLevel": 2,
      "raidsSinceStarted": 0,
      "timeAvailable": 1717992154821
    },
    "10": {
      "currentLevel": 2,
      "raidsSinceStarted": 0,
      "timeAvailable": 1717992154821
    },
    "16": {
      "currentLevel": 1,
      "raidsSinceStarted": 0,
      "timeAvailable": 1717992154821
    },
    "21": {
      "currentLevel": 1,
      "raidsSinceStarted": 0,
      "timeAvailable": 1717991813221
    },
    "22": {
      "currentLevel": 4,
      "raidsSinceStarted": 0,
      "timeAvailable": 1717992154821
    },
    "23": {
      "currentLevel": 1,
      "raidsSinceStarted": 0,
      "timeAvailable": 1717992154821
    }
  },
  "quests": {
    "6660879c652f9a5baa000001": {
      "raidsSinceStarted": 0
    },
    "5bc4776586f774512d07cf05": {
      "raidsSinceStarted": 0
    },
    "5d25aed386f77442734d25d2": {
      "raidsSinceStarted": 0
    },
    "5bc479e586f7747f376c7da3": {
      "raidsSinceStarted": 0
    },
    "5ac2426c86f774138762edfe": {
      "raidsSinceStarted": 0
    },
    "5ac2428686f77412450b42bf": {
      "raidsSinceStarted": 0
    },
    "5ac345dc86f774288030817f": {
      "raidsSinceStarted": 0
    },
    "5a27b7a786f774579c3eb376": {
      "raidsSinceStarted": 0
    },
    "5c1234c286f77406fa13baeb": {
      "raidsSinceStarted": 0
    },
    "ARTT_4": {
      "raidsSinceStarted": 0
    },
    "painter_5": {
      "raidsSinceStarted": 0
    },
    "5968eb3186f7741dde183a4d": {
      "raidsSinceStarted": 0
    },
    "5ae448bf86f7744d733e55ee": {
      "raidsSinceStarted": 0
    },
    "5ae448e586f7744dcf0c2a67": {
      "raidsSinceStarted": 0
    },
    "638fcd23dc65553116701d33": {
      "raidsSinceStarted": 0
    },
    "5969f9e986f7741dde183a50": {
      "raidsSinceStarted": 0
    },
    "5c0d190cd09282029f5390d8": {
      "raidsSinceStarted": 0
    },
    "6193850f60b34236ee0483de": {
      "raidsSinceStarted": 0
    },
    "5979eee086f774311955e614": {
      "raidsSinceStarted": 0
    },
    "5d25e48d86f77408251c4bfb": {
      "raidsSinceStarted": 0
    },
    "Scorpion_1_1": {
      "raidsSinceStarted": 28
    },
    "Scorpion_Event_June_1": {
      "raidsSinceStarted": 28
    },
    "Scorpion_2_1": {
      "raidsSinceStarted": 0
    },
    "Scorpion_4_1": {
      "raidsSinceStarted": 0
    },
    "59c124d686f774189b3c843f": {
      "raidsSinceStarted": 0
    }
  }
}