    [Drink]
        "Pack of Russian Army pineapple juice": Avg:5 | Max:5
        "Bottle of Tarkovskaya vodka": Avg:4 | Max:4
        "Can of Hot Rod energy drink": Avg:4 | Max:4
        "Pack of milk": Avg:4 | Max:4
        "Pack of Grand juice": Avg:3 | Max:3
        "Pack of apple juice": Avg:3 | Max:3
        "Bottle of "Norvinskiy Yadreniy" premium kvass (0.6L)": Avg:3 | Max:3
        "Emergency Water Ration": Avg:2 | Max:2
        "Pack of Vita juice": Avg:2 | Max:2
        "Can of Ice Green tea": Avg:1 | Max:1
    [AmmoBox]
        "5.45x39mm PP gs ammo pack (30 pcs)": Avg:5 | Max:5
        "7.62x39mm T-45M1 gzh ammo pack (20 pcs)": Avg:4 | Max:4
        "4.6x30mm JSP SX ammo pack (40 pcs)": Avg:3 | Max:3
        "7.62x39mm PS gzh ammo pack (20 pcs)": Avg:3 | Max:3
        "9x19mm Pst gzh ammo pack (16 pcs)": Avg:3 | Max:3
        "5.45x39mm PS gs ammo pack (120 pcs)": Avg:2 | Max:2
        "5.45x39mm PS gs ammo pack (30 pcs)": Avg:2 | Max:2
        "9x18mm PMM PstM gzh ammo pack (16 pcs)": Avg:2 | Max:2
        "9x18mm PM PPT gzh ammo pack (16 pcs)": Avg:2 | Max:2
        "9x18mm PM PBM gzh ammo pack (16 pcs)": Avg:2 | Max:2
        "7.62x39mm FMJ ammo pack (20 pcs)": Avg:2 | Max:2
        "5.45x39mm PRS gs ammo pack (120 pcs)": Avg:1 | Max:1
        "5.56x45mm SSA AP ammo pack (100 pcs)": Avg:1 | Max:1
        "20/70 "Poleva-6u" slug ammo pack (25 pcs)": Avg:1 | Max:1
        "12/70 Copper Sabot Premier HP slug ammo pack (25 pcs)": Avg:1 | Max:1
        "5.45x39mm US gs ammo pack (120 pcs)": Avg:1 | Max:1
        "7.62x54mm R HP BT ammo pack (20 pcs)": Avg:1 | Max:1
        "9x18mm PM SP7 gzh ammo pack (16 pcs)": Avg:1 | Max:1
        "9x18mm PM PS gs PPO ammo pack (16 pcs)": Avg:1 | Max:1
        "5.45x39mm US gs ammo pack (30 pcs)": Avg:1 | Max:1
        "7.62x39mm SP ammo pack (20 pcs)": Avg:1 | Max:1
        "5.45x39mm BP gs ammo pack (30 pcs)": Avg:1 | Max:1
    [Drugs]
        "Morphine injector": Avg:4 | Max:4
        "Augmentin antibiotic pills": Avg:2 | Max:2
        "Analgin painkillers": Avg:1 | Max:1
    [Food]
        "Pack of oat flakes": Avg:4 | Max:4
        "Pack of Tarker dried meat": Avg:3 | Max:3
        "MRE ration pack": Avg:3 | Max:3
        "Can of beef stew (Small)": Avg:2 | Max:2
        "Pack of sugar": Avg:2 | Max:2
        "Can of condensed milk": Avg:2 | Max:2
        "Pack of instant noodles": Avg:2 | Max:2
        "Can of sprats": Avg:1 | Max:1
        "Can of pacific saury": Avg:1 | Max:1
        "Rye croutons": Avg:1 | Max:1
        "Can of beef stew (Large)": Avg:1 | Max:1
        "Iskra ration pack": Avg:1 | Max:1
        "Can of herring": Avg:1 | Max:1
        "Army crackers": Avg:1 | Max:1
    [BuildingMaterial]
        "Silicone tube": Avg:3 | Max:3
        "Xenomorph sealing foam": Avg:1 | Max:1
        "Insulating tape": Avg:1 | Max:1
        "Duct tape": Avg:1 | Max:1
        "Piece of plexiglass": Avg:1 | Max:1
    [Jewelry]
        "Horse figurine": Avg:3 | Max:3
        "Raven figurine": Avg:1 | Max:1
        "Politician Mutkevich figurine": Avg:1 | Max:1
    [Tool]
        "Old firesteel": Avg:2 | Max:2
        "Construction measuring tape": Avg:2 | Max:2
        "Round pliers": Avg:1 | Max:1
        "Wrench": Avg:1 | Max:1
        "Fierce Blow sledgehammer": Avg:1 | Max:1
    [Armor]
        "PACA Soft Armor": Avg:2 | Max:2
    [Money]
        "Dollars": Avg:2 | Max:2
        "Euros": Avg:1 | Max:1
    [Info]
        "Encrypted message": Avg:1 | Max:1
        "Secure Folder 0052": Avg:1 | Max:1
    [Electronics]
        "Single-axis Fiber Optic Gyroscope #1": Avg:1 | Max:1
        "Motor Controller #1": Avg:1 | Max:1
    [MedicalSupplies]
        "Blood sample": Avg:1 | Max:1
        "Bottle of saline solution": Avg:1 | Max:1
        "Pile of meds": Avg:1 | Max:1
        "LEDX Skin Transilluminator": Avg:1 | Max:1
    [Collimator]
        "Hensoldt RV red dot sight": Avg:1 | Max:1
    [FlashHider]
        "AK Zenit DTK-1 7.62x39/5.45x39 muzzle brake-compensator": Avg:1 | Max:1
        "AR-10 TAA ZK-38 7.62x51 muzzle brake": Avg:1 | Max:1
        "Mosin Rifle Tacfire Tanker Style 7.62x54R muzzle brake": Avg:1 | Max:1
    [TacticalCombo]
        "MAWL-C1+ tactical device": Avg:1 | Max:1
        "Steiner LAS/TAC 2 tactical flashlight": Avg:1 | Max:1
        "Zenit Perst-3 tactical device": Avg:1 | Max:1
        "Insight WMX200 tactical flashlight": Avg:1 | Max:1
    [Silencer]
        "VPO-101 "Vepr-Hunter" Rotor 43 7.62x51 muzzle brake-compensator": Avg:1 | Max:1
        "Gemtech ONE multi-caliber sound suppressor": Avg:1 | Max:1
        "HK G28 B&T QD 7.62x51 sound suppressor": Avg:1 | Max:1
        "AAC Illusion 9 9x19 sound suppressor": Avg:1 | Max:1
    [Stimulator]
        ""Obdolbos" cocktail injector": Avg:1 | Max:1
    [Barrel]
        "M870 12ga 355mm barrel": Avg:1 | Max:1
    [KeyMechanical]
        "Health Resort east wing room 316 key": Avg:1 | Max:1
    [MedKit]
        "Grizzly medical kit": Avg:1 | Max:1
        "Car first aid kit": Avg:1 | Max:1
        "Salewa first aid kit": Avg:1 | Max:1
    [Medical]
        "CAT hemostatic tourniquet": Avg:1 | Max:1
        "CALOK-B hemostatic applicator": Avg:1 | Max:1
        "Aluminum splint": Avg:1 | Max:1
    [AssaultScope]
        "SIG Sauer BRAVO4 4x30 scope": Avg:1 | Max:1
    [Battery]
        "AA Battery": Avg:1 | Max:1
    [PistolGrip]
        "SVDS Lynx Arms AK-series pistol grip adapter": Avg:1 | Max:1
    [Keycard]
        "TerraGroup Labs keycard (Violet)": Avg:1 | Max:1
    [Foregrip]
        "Magpul M-LOK AFG tactical foregrip (Black)": Avg:1 | Max:1
    [Fuel]
        "Expeditionary fuel tank": Avg:1 | Max:1
    [MuzzleCombo]
        "SilencerCo Omega 45k Piston Mount adapter": Avg:1 | Max:1
    [Handguard]
        "MPX Lancer OEM 14 inch M-LOK handguard": Avg:1 | Max:1
    [OpticScope]
        "Schmidt & Bender PM II 3-12x50 34mm riflescope": Avg:1 | Max:1
